chamfer_ext.cpython-39-darwin.so
chamfer/__init__.py
chamfer/src/kd_tree.cpp
chamfer/src/kd_tree.hpp
chamfer/src/metal_bridge.mm
chamfer_metal-0.1.0.dist-info/licenses/LICENSE
chamfer_metal-0.1.0.dist-info/METADATA
chamfer_metal-0.1.0.dist-info/WHEEL
chamfer_metal-0.1.0.dist-info/top_level.txt
chamfer_metal-0.1.0.dist-info/RECORD
